gvol/__init__.py
gvol/client.py
gvol/queries.py
gvol/types.py
gvol-0.6.2.dist-info/METADATA
gvol-0.6.2.dist-info/WHEEL
gvol-0.6.2.dist-info/RECORD
